ps3/__init__.py
ps3/configuration_ps3.py
ps3/image_processing_ps3.py
ps3/modeling_ps3.py
ps3/modeling_ps3_text.py
ps3/tokenization_ps3.py
ps3/utils_radio_adapter_mlp.py
ps3_torch-0.1.3.dist-info/licenses/LICENSE.md
ps3_torch-0.1.3.dist-info/licenses/LICENSE_for_PS3.md
ps3_torch-0.1.3.dist-info/METADATA
ps3_torch-0.1.3.dist-info/WHEEL
ps3_torch-0.1.3.dist-info/top_level.txt
ps3_torch-0.1.3.dist-info/RECORD
